pyswitchcontroller/__init__.py
pyswitchcontroller/controller.py
pyswitchcontroller/py.typed
pyswitchcontroller-2023.11.8.14.8.dist-info/METADATA
pyswitchcontroller-2023.11.8.14.8.dist-info/WHEEL
pyswitchcontroller-2023.11.8.14.8.dist-info/licenses/LICENSE
pyswitchcontroller-2023.11.8.14.8.dist-info/RECORD
