Metadata-Version: 2.1
Name: pyswitchcontroller
Version: 2023.11.8.14.8
Summary: A Python library for controlling the Nintendo Switch via USB.
Project-URL: Homepage, https://github.com/Nakanishi123/pyswitchcontroller
Author-email: Nakanishi <45790603+Nakanishi123@users.noreply.github.com>
License-Expression: GPL-3.0
License-File: LICENSE
Classifier: License :: OSI Approved :: GNU General Public License v3 (GPLv3)
Classifier: Programming Language :: Python :: 3
Classifier: Programming Language :: Python :: 3 :: Only
Classifier: Programming Language :: Python :: 3.8
Classifier: Programming Language :: Python :: 3.9
Classifier: Programming Language :: Python :: 3.10
Classifier: Programming Language :: Python :: 3.11
Requires-Python: >=3.8
Requires-Dist: pyftdi>=0.55.0
Requires-Dist: pyqt6>=6.6.0
